threefive/__init__.py
threefive/aac.py
threefive/base.py
threefive/bitn.py
threefive/bump.py
threefive/commands.py
threefive/crc.py
threefive/crctable.py
threefive/cue.py
threefive/descriptors.py
threefive/encode.py
threefive/gums.py
threefive/hls.py
threefive/hlstags.py
threefive/iframes.py
threefive/new_reader.py
threefive/packetdata.py
threefive/pmt.py
threefive/section.py
threefive/segment.py
threefive/segmentation.py
threefive/sixfix.py
threefive/speedo.py
threefive/stream.py
threefive/streamtypes.py
threefive/stuff.py
threefive/superkabuki.py
threefive/throttle.py
threefive/upids.py
threefive/uxp.py
threefive/version.py
threefive/words.py
threefive/xml.py
threefive-3.0.71.data/scripts/threefive
threefive-3.0.71.dist-info/licenses/LICENSE
threefive-3.0.71.dist-info/METADATA
threefive-3.0.71.dist-info/WHEEL
threefive-3.0.71.dist-info/top_level.txt
threefive-3.0.71.dist-info/RECORD
